CONTRIBUTING.rst
LICENSE
MANIFEST.in
README.rst
setup.cfg
setup.py
funsize/__init__.py
funsize/balrog.py
funsize/scheduler.py
funsize/utils.py
funsize/worker.py
funsize.egg-info/PKG-INFO
funsize.egg-info/SOURCES.txt
funsize.egg-info/dependency_links.txt
funsize.egg-info/entry_points.txt
funsize.egg-info/not-zip-safe
funsize.egg-info/requires.txt
funsize.egg-info/top_level.txt
funsize/data/ca-bundle.crt
funsize/data/docker-worker-pub.pem
funsize/data/generate_update_platforms.py
funsize/data/generate_update_platforms.sh
funsize/data/mozilla-root.crt
funsize/data/platform_map.json
funsize/tasks/funsize.yml