Metadata-Version: 1.0
Name: funsize
Version: 0.62
Summary: Funsize Scheduler
Home-page: UNKNOWN
Author: Mozilla Release Engineering
Author-email: UNKNOWN
License: UNKNOWN
Platform: UNKNOWN
